{
  "theta": 0,
  "alpha": [
    [0, 0, 0],
    [0, 0, 0],
    [0, 0, 0],
    [0, 0, 0],
    [0, 0, 0],
    [0, 0, 0],
    [0, 0, 0],
    [0, 0, 0],
    [0, 0, 0],
    [0, 0, 0],
    [0, 0, 0],
    [0, 0, 0],
    [0, 0, 0],
    [0, 0, 0],
    [0, 0, 0],
    [0, 0, 0],
    [0, 0, 0],
    [0, 0, 0],
    [0, 0, 0],
    [0, 0, 0],
    [0, 0, 0],
    [0, 0, 0],
    [0, 0, 0],
    [0, 0, 0],
    [0, 0, 0],
    [0, 0, 0],
    [0, 0, 0],
    [0, 0, 0],
    [0, 0, 0],
    [0, 0, 0],
    [0, 0, 0],
    [0, 0, 0],
    [0, 0, 0],
    [0, 0, 0],
    [0, 0, 0],
    [0, 0, 0],
    [0, 0, 0],
    [0, 0, 0]
  ],
  "Omega": [
    [10, -3, -3],
    [-3, 135, -65],
    [-3, -65, 135]
  ],
  "beta": [0, 0, 0, 0, 0, 0, 0, 0],
  "phi": 0.01,
  "gamma": [0, 0, 0]
}
